prapi/Circle.py
prapi/FDR.py
prapi/GLM_MS_paired.py
prapi/GLM_MS_unpaired.py
prapi/MATS_LRT.py
prapi/Pacbio_edger.py
prapi/Pacbio_mats.py
prapi/Pacbio_mats_s2.py
prapi/Pacbio_untils_edger.py
prapi/Pacbio_v16.py
prapi/Pacbio_v16_circle.py
prapi/__init__.py
prapi/alignPacBio.py
prapi/apa_v1.py
prapi/asas_v3.py
prapi/asas_v4_cuff.py
prapi/ati_v1.py
prapi/check_input.py
prapi/circle_draw.py
prapi/cleanAlignments.py
prapi/convertSam.py
prapi/de_apa_v1.py
prapi/de_nat_v1.py
prapi/genemode.py
prapi/genemode_v2.py
prapi/getGeneExpr.GTF.SAM.py
prapi/human.py
prapi/inclusion_level.py
prapi/joinFiles.py
prapi/joinfiles.py
prapi/m6A.py
prapi/miss_annotation_gene.py
prapi/nat_v1.py
prapi/novel_gene.py
prapi/novel_gene_calclute.py
prapi/sam_to_gff_trim_3.py
prapi/sam_to_gff_trim_5.py
prapi/sam_to_gff_trim_none.py
prapi/setup.py
prapi/utils.py
prapi/visual_basic.py
prapi/visual_basic_all.py
prapi/visual_basic_pacbio.py
prapi/visual_circle_pacbio.py
prapi/visual_de_apa.py
prapi/visual_de_apa_all.py
prapi/visual_de_apa_pacbio.py
prapi/visual_de_as.py
prapi/visual_de_as_all.py
prapi/visual_de_as_pacbio.py
prapi/visual_de_circle_pacbio.py
prapi/visual_de_nat_all.py
prapi/visual_de_nat_pacbio.py
prapi-6.2.0.data/scripts/Circle.py
prapi-6.2.0.data/scripts/DEGseq_circv1.R
prapi-6.2.0.data/scripts/FDR.py
prapi-6.2.0.data/scripts/GLM_MS_paired.py
prapi-6.2.0.data/scripts/GLM_MS_unpaired.py
prapi-6.2.0.data/scripts/MATS_LRT.py
prapi-6.2.0.data/scripts/MATS_LRT.sh
prapi-6.2.0.data/scripts/Pacbio.sh
prapi-6.2.0.data/scripts/Pacbio.txt
prapi-6.2.0.data/scripts/Pacbio_edger.py
prapi-6.2.0.data/scripts/Pacbio_mats.py
prapi-6.2.0.data/scripts/Pacbio_mats.sh
prapi-6.2.0.data/scripts/Pacbio_mats_cuff.sh
prapi-6.2.0.data/scripts/Pacbio_mats_s2.py
prapi-6.2.0.data/scripts/Pacbio_untils_edger.py
prapi-6.2.0.data/scripts/Pacbio_v16.py
prapi-6.2.0.data/scripts/Pacbio_v16_circle.py
prapi-6.2.0.data/scripts/__init__.py
prapi-6.2.0.data/scripts/alignPacBio.py
prapi-6.2.0.data/scripts/apa_v1.py
prapi-6.2.0.dist-info/METADATA
prapi-6.2.0.dist-info/WHEEL
prapi-6.2.0.dist-info/top_level.txt
prapi-6.2.0.dist-info/RECORD
