Metadata-Version: 2.1
Name: prapi
Version: 6.2.0
Summary: Transcriptome Analysis Pipeline for Isoform Sequencing
Home-page: http://www.bioinfor.org/tool/PRAPI/
Author: gaoyubang
Author-email: 1489582340@qq.com
License: MIT
Platform: UNKNOWN
Classifier: Development Status :: 3 - Alpha
Classifier: Environment :: Console
Classifier: License :: OSI Approved :: MIT License
Classifier: Operating System :: POSIX
Classifier: Programming Language :: Python
Classifier: Topic :: Scientific/Engineering :: Bio-Informatics
Requires: SpliceGrapher
Requires: numpy
Requires: matplotlib
Requires: pysam
Requires: pycairo
